vb_toolbox/__init__.py
vb_toolbox/app.py
vb_toolbox/io.py
vb_toolbox/numerics.py
vb_toolbox/vb_index.py
VBIndex-0.0.4.dist-info/LICENSE
VBIndex-0.0.4.dist-info/METADATA
VBIndex-0.0.4.dist-info/WHEEL
VBIndex-0.0.4.dist-info/entry_points.txt
VBIndex-0.0.4.dist-info/top_level.txt
VBIndex-0.0.4.dist-info/RECORD
