Metadata-Version: 2.1
Name: VBIndex
Version: 0.0.4
Summary: Library and command-line tool to calculate the Vogt-Bailey index of a dataset
Home-page: https://github.com/VBIndex/py_vbindex
Author: Lucas da Costa Campos
Author-email: lqccampos@gmail.com
License: UNKNOWN
Platform: UNKNOWN
Classifier: Programming Language :: Python :: 3
Classifier: License :: OSI Approved :: GNU General Public License v3 (GPLv3)
Classifier: Operating System :: OS Independent
Classifier: Topic :: Scientific/Engineering :: Medical Science Apps.
Requires-Python: >=3.6
Requires-Dist: numpy
Requires-Dist: scipy
Requires-Dist: nibabel
Requires-Dist: multiprocess
